{"cameraMode":{"drawMode":0,"name":"Shaded","section":"Shading Mode"},"sceneLighting":true,"audioPlay":false,"sceneViewState":{"m_AlwaysRefresh":true,"showFog":true,"showSkybox":true,"showFlares":true,"showImageEffects":true,"showParticleSystems":true,"showVisualEffectGraphs":true,"m_FxEnabled":true},"in2DMode":false,"pivot":{"x":7.124013900756836,"y":5.341512680053711,"z":-2.62795352935791},"rotation":{"x":-0.195895254611969,"y":0.41599684953689577,"z":-0.0926491767168045,"w":-0.8832934498786926},"size":1.7025995254516602,"orthographic":false}